scitex_writer/__init__.py
scitex_writer/__main__.py
scitex_writer/_branding.py
scitex_writer/_cli.py
scitex_writer/_server.py
scitex_writer/bib.py
scitex_writer/compile.py
scitex_writer/figures.py
scitex_writer/project.py
scitex_writer/tables.py
scitex_writer/writer.py
scitex_writer/_cli/__init__.py
scitex_writer/_cli/bib.py
scitex_writer/_cli/compile.py
scitex_writer/_cli/figures.py
scitex_writer/_cli/guidelines.py
scitex_writer/_cli/introspect.py
scitex_writer/_cli/mcp.py
scitex_writer/_cli/prompts.py
scitex_writer/_cli/tables.py
scitex_writer/_compile/__init__.py
scitex_writer/_compile/_compile_async.py
scitex_writer/_compile/_compile_unified.py
scitex_writer/_compile/_parser.py
scitex_writer/_compile/_runner.py
scitex_writer/_compile/_validator.py
scitex_writer/_compile/manuscript.py
scitex_writer/_compile/revision.py
scitex_writer/_compile/supplementary.py
scitex_writer/_dataclasses/__init__.py
scitex_writer/_dataclasses/config/_CONSTANTS.py
scitex_writer/_dataclasses/config/_WriterConfig.py
scitex_writer/_dataclasses/config/__init__.py
scitex_writer/_dataclasses/contents/_ManuscriptContents.py
scitex_writer/_dataclasses/contents/_RevisionContents.py
scitex_writer/_dataclasses/contents/_SupplementaryContents.py
scitex_writer/_dataclasses/contents/__init__.py
scitex_writer/_dataclasses/core/_Document.py
scitex_writer/_dataclasses/core/_DocumentSection.py
scitex_writer/_dataclasses/core/__init__.py
scitex_writer/_dataclasses/results/_CompilationResult.py
scitex_writer/_dataclasses/results/_LaTeXIssue.py
scitex_writer/_dataclasses/results/_SaveSectionsResponse.py
scitex_writer/_dataclasses/results/_SectionReadResponse.py
scitex_writer/_dataclasses/results/__init__.py
scitex_writer/_dataclasses/tree/_ConfigTree.py
scitex_writer/_dataclasses/tree/_ManuscriptTree.py
scitex_writer/_dataclasses/tree/_RevisionTree.py
scitex_writer/_dataclasses/tree/_ScriptsTree.py
scitex_writer/_dataclasses/tree/_SharedTree.py
scitex_writer/_dataclasses/tree/_SupplementaryTree.py
scitex_writer-2.4.0.dist-info/METADATA
scitex_writer-2.4.0.dist-info/WHEEL
scitex_writer-2.4.0.dist-info/entry_points.txt
scitex_writer-2.4.0.dist-info/licenses/LICENSE
scitex_writer-2.4.0.dist-info/RECORD
