Metadata-Version: 2.4
Name: scitex-writer
Version: 2.4.0
Summary: LaTeX manuscript compilation system for scientific documents with MCP server
Project-URL: Homepage, https://github.com/ywatanabe1989/scitex-writer
Project-URL: Documentation, https://github.com/ywatanabe1989/scitex-writer#readme
Project-URL: Repository, https://github.com/ywatanabe1989/scitex-writer.git
Project-URL: Issues, https://github.com/ywatanabe1989/scitex-writer/issues
Author-email: Yusuke Watanabe <ywatanabe@scitex.ai>
License-Expression: AGPL-3.0
License-File: LICENSE
Keywords: academic,bibliography,bibtex,compilation,latex,manuscript,mcp,mcp-server,paper,scientific-writing
Classifier: Development Status :: 4 - Beta
Classifier: Environment :: Console
Classifier: Intended Audience :: Science/Research
Classifier: License :: OSI Approved :: GNU Affero General Public License v3
Classifier: Operating System :: OS Independent
Classifier: Programming Language :: Python :: 3
Classifier: Programming Language :: Python :: 3.10
Classifier: Programming Language :: Python :: 3.11
Classifier: Programming Language :: Python :: 3.12
Classifier: Programming Language :: Python :: 3.13
Classifier: Topic :: Scientific/Engineering
Classifier: Topic :: Text Processing :: Markup :: LaTeX
Requires-Python: >=3.10
Requires-Dist: fastmcp>=2.0.0
Provides-Extra: dev
Requires-Dist: pre-commit>=3.5.0; extra == 'dev'
Requires-Dist: pytest-cov>=4.0.0; extra == 'dev'
Requires-Dist: pytest-xdist>=3.0.0; extra == 'dev'
Requires-Dist: pytest>=7.0.0; extra == 'dev'
